mcschemes/__init__.py
mcschemes/enums.py
mcschemes/py.typed
mcschemes/specials.py
mcschemes/typings.py
mcschemes/assetindex/__init__.py
mcschemes/assetindex/nodes.py
mcschemes/clientmanifest/__init__.py
mcschemes/clientmanifest/nodes.py
mcschemes/mojangjava/__init__.py
mcschemes/mojangjava/nodes.py
mcschemes/tools/__init__.py
mcschemes/tools/rules.py
mcschemes/tools/parser/__init__.py
mcschemes/tools/parser/converters.py
mcschemes/versionattrs/__init__.py
mcschemes/versionattrs/nodes.py
mcschemes/versionmanifest/__init__.py
mcschemes/versionmanifest/nodes.py
minecraft_schemes-0.3.0.dist-info/licenses/LICENSE
minecraft_schemes-0.3.0.dist-info/METADATA
minecraft_schemes-0.3.0.dist-info/WHEEL
minecraft_schemes-0.3.0.dist-info/top_level.txt
minecraft_schemes-0.3.0.dist-info/RECORD
