Metadata-Version: 2.4
Name: minecraft-schemes
Version: 0.3.0
Summary: Parse Minecraft-relative JSON to structured objects
Author-email: Izanagi Tokiyuki <izanagitokiyuki@noreply.codeberg.org>
License-Expression: MulanPSL-2.0
Project-URL: Repository, https://codeberg.org/IzanagiTokiyuki/minecraft-schemes
Project-URL: Issues, https://codeberg.org/IzanagiTokiyuki/minecraft-schemes/issues
Project-URL: Changelog, https://codeberg.org/IzanagiTokiyuki/minecraft-schemes/src/branch/master/HISTORY.md
Keywords: minecraft,scheme
Classifier: Programming Language :: Python :: 3 :: Only
Classifier: Programming Language :: Python :: 3.12
Classifier: Programming Language :: Python :: 3.13
Classifier: Programming Language :: Python :: 3.14
Requires-Python: >=3.12
License-File: LICENSE
Requires-Dist: attrs>=25.4.0
Requires-Dist: cattrs>=25.3.0
Requires-Dist: pendulum>=3.1.0
Requires-Dist: typing-extensions>=4.15.0
Dynamic: license-file
